{
	"S SS": {
		"∀": 34,
		"∃": 36,
		"∋": 39,
		"∗": 42,
		"−": 45,
		"≅": 64,
		"Α": 65,
		"Β": 66,
		"Χ": 67,
		"Δ": 68,
		"Ε": 69,
		"Φ": 70,
		"Γ": 71,
		"Η": 72,
		"Ι": 73,
		"ϑ": 74,
		"Κ": 75,
		"Λ": 76,
		"Μ": 77,
		"Ν": 78,
		"Ο": 79,
		"Π": 80,
		"Θ": 81,
		"Ρ": 82,
		"Σ": 83,
		"Τ": 84,
		"Υ": 85,
		"ς": 86,
		"Ω": 87,
		"Ξ": 88,
		"Ψ": 89,
		"Ζ": 90,
		"∴": 92,
		"⊥": 94,
		"\uF8E5": 96,
		"α": 97,
		"β": 98,
		"χ": 99,
		"δ": 100,
		"ε": 101,
		"ϕ": 102,
		"γ": 103,
		"η": 104,
		"ι": 105,
		"φ": 106,
		"κ": 107,
		"λ": 108,
		"μ": 109,
		"ν": 110,
		"ο": 111,
		"π": 112,
		"θ": 113,
		"ρ": 114,
		"σ": 115,
		"τ": 116,
		"υ": 117,
		"ϖ": 118,
		"ω": 119,
		"ξ": 120,
		"ψ": 121,
		"ζ": 122,
		"∼": 126,
		"€": 160,
		"Υ": 161,
		"′": 162,
		"≤": 163,
		"⁄": 164,
		"∞": 165,
		"ƒ": 166,
		"♣": 167,
		"♦": 168,
		"♥": 169,
		"♠": 170,
		"↔": 171,
		"←": 172,
		"↑": 173,
		"→": 174,
		"↓": 175,
		"°": 176,
		"±": 177,
		"″": 178,
		"≥": 179,
		"×": 180,
		"∝": 181,
		"∂": 182,
		"·": 183,
		"÷": 184,
		"≠": 185,
		"≡": 186,
		"≈": 187,
		"…": 188,
		"\u23D0": 189,
		"⎯": 190,
		"↵": 191,
		"ℵ": 192,
		"ℑ": 193,
		"ℜ": 194,
		"℘": 195,
		"⊗": 196,
		"⊕": 197,
		"∅": 198,
		"∩": 199,
		"∪": 200,
		"⊃": 201,
		"⊇": 202,
		"⊄": 203,
		"⊂": 204,
		"⊆": 205,
		"∈": 206,
		"∉": 207,
		"/_": 208,
		"∇": 209,
		"\uF8E8": 210,
		"\uF8E9": 211,
		"\uF8EA": 212,
		"∏": 213,
		"√": 214,
		"⋅": 215,
		"¬": 216,
		"∧": 217,
		"∨": 218,
		"⇔": 219,
		"⇐": 220,
		"⇑": 221,
		"⇒": 222,
		"⇓": 223,
		"◊": 224,
		"⟨": 225,
		"®": 226,
		"©": 227,
		"™": 228,
		"∑": 229,
		"⎛": 230,
		"⎜": 231,
		"⎝": 232,
		"⎡": 233,
		"⎢": 234,
		"⎣": 235,
		"⎧": 236,
		"⎨": 237,
		"⎩": 238,
		"⎪": 239,
		"⟩": 241,
		"∫": 242,
		"⌠": 243,
		"⎮": 244,
		"⌡": 245,
		"⎞": 246,
		"⎟": 247,
		"⎠": 248,
		"⎤": 249,
		"⎥": 250,
		"⎦": 251,
		"⎫": 252,
		"⎬": 253,
		"⎭": 254,
		"\uF8FF": 256
	}
}
